{"ts":1770043208709,"data":[{"idPlayer":"34155031","idTeam":"134571","idTeam2":"0","idTeamNational":null,"idAPIfootball":"39122","idPlayerManager":null,"idWikidata":null,"idTransferMkt":"202925","idESPN":"173355","strNationality":"Norway","strPlayer":"Bard Finne","strPlayerAlternate":"","strTeam":"Brann","strTeam2":"","strSport":"Soccer","intSoccerXMLTeamID":"61","dateBorn":"1995-02-13","dateDied":null,"strNumber":"11","dateSigned":"2014-08-17","strSigning":"Signed","strWage":"","strOutfitter":"","strKit":"","strAgent":"goOn as","strBirthLocation":"Bergen, Norway","strEthnicity":"White","strStatus":"Active","strDescriptionEN":"Bård Finne (born 13 February 1995) is a Norwegian football player who plays as a forward for Vålerenga Fotball. Hailing from Bergen, he started his professional career in Brann. Finne has represented Norway from under-15 to under-21 level.","strDescriptionDE":null,"strDescriptionFR":null,"strDescriptionCN":null,"strDescriptionIT":null,"strDescriptionJP":null,"strDescriptionRU":null,"strDescriptionES":null,"strDescriptionPT":null,"strDescriptionSE":null,"strDescriptionNL":null,"strDescriptionHU":null,"strDescriptionNO":null,"strDescriptionIL":null,"strDescriptionPL":null,"strGender":"Male","strSide":"","strPosition":"Forward","strCollege":null,"strFacebook":"","strWebsite":"","strTwitter":"","strInstagram":"","strYoutube":"","strHeight":"1.79 m (5 ft 10 1⁄2 in)","strWeight":"152 lbs","intLoved":"0","strThumb":null,"strPoster":null,"strCutout":null,"strCartoon":null,"strRender":null,"strBanner":null,"strFanart1":null,"strFanart2":null,"strFanart3":null,"strFanart4":null,"strCreativeCommons":"No","strLocked":"unlocked","strLastName":"Finne"},{"idPlayer":"34346383","idTeam":"134571","idTeam2":null,"idTeamNational":null,"idAPIfootball":"304373","idPlayerManager":null,"idWikidata":null,"idTransferMkt":null,"idESPN":null,"strNationality":"Belgium","strPlayer":"Denzel De Roeve","strPlayerAlternate":null,"strTeam":"Brann","strTeam2":null,"strSport":"Soccer","intSoccerXMLTeamID":null,"dateBorn":"2004-08-10","dateDied":null,"strNumber":null,"dateSigned":null,"strSigning":null,"strWage":null,"strOutfitter":null,"strKit":null,"strAgent":null,"strBirthLocation":", Belgium","strEthnicity":null,"strStatus":null,"strDescriptionEN":null,"strDescriptionDE":null,"strDescriptionFR":null,"strDescriptionCN":null,"strDescriptionIT":null,"strDescriptionJP":null,"strDescriptionRU":null,"strDescriptionES":null,"strDescriptionPT":null,"strDescriptionSE":null,"strDescriptionNL":null,"strDescriptionHU":null,"strDescriptionNO":null,"strDescriptionIL":null,"strDescriptionPL":null,"strGender":"Male","strSide":null,"strPosition":"Defender","strCollege":null,"strFacebook":null,"strWebsite":null,"strTwitter":null,"strInstagram":null,"strYoutube":null,"strHeight":"","strWeight":"","intLoved":"0","strThumb":null,"strPoster":null,"strCutout":null,"strCartoon":null,"strRender":null,"strBanner":null,"strFanart1":null,"strFanart2":null,"strFanart3":null,"strFanart4":null,"strCreativeCommons":"No","strLocked":"unlocked","strLastName":"Roeve"},{"idPlayer":"34245038","idTeam":"134571","idTeam2":null,"idTeamNational":null,"idAPIfootball":"197625","idPlayerManager":null,"idWikidata":null,"idTransferMkt":null,"idESPN":null,"strNationality":"Iceland","strPlayer":"Eggert Guðmundsson","strPlayerAlternate":"","strTeam":"Brann","strTeam2":"","strSport":"Soccer","intSoccerXMLTeamID":null,"dateBorn":"2004-02-08","dateDied":null,"strNumber":"11","dateSigned":null,"strSigning":"","strWage":"","strOutfitter":"","strKit":"","strAgent":"","strBirthLocation":", Iceland","strEthnicity":"White","strStatus":"Active","strDescriptionEN":"Eggert Aron Guðmundsson (born 8 February 2004) is an Icelandic football player who plays as a midfielder for Swedish club Elfsborg and the Iceland national team.","strDescriptionDE":null,"strDescriptionFR":null,"strDescriptionCN":null,"strDescriptionIT":null,"strDescriptionJP":null,"strDescriptionRU":null,"strDescriptionES":null,"strDescriptionPT":null,"strDescriptionSE":null,"strDescriptionNL":null,"strDescriptionHU":null,"strDescriptionNO":null,"strDescriptionIL":null,"strDescriptionPL":null,"strGender":"Male","strSide":"","strPosition":"Midfielder","strCollege":null,"strFacebook":"","strWebsite":"","strTwitter":"","strInstagram":"","strYoutube":"","strHeight":"177 cm","strWeight":"70 kg","intLoved":"0","strThumb":"https://r2.thesportsdb.com/images/media/player/thumb/g60qtt1724858121.jpg","strPoster":null,"strCutout":"https://r2.thesportsdb.com/images/media/player/cutout/yxi7xh1724858139.png","strCartoon":null,"strRender":null,"strBanner":null,"strFanart1":null,"strFanart2":null,"strFanart3":null,"strFanart4":null,"strCreativeCommons":"No","strLocked":"unlocked","strLastName":"Guðmundsson"},{"idPlayer":"34252048","idTeam":"134571","idTeam2":null,"idTeamNational":null,"idAPIfootball":"416062","idPlayerManager":null,"idWikidata":null,"idTransferMkt":null,"idESPN":null,"strNationality":"Norway","strPlayer":"Eivind Fauske Helland","strPlayerAlternate":null,"strTeam":"Brann","strTeam2":null,"strSport":"Soccer","intSoccerXMLTeamID":null,"dateBorn":"2005-04-25","dateDied":null,"strNumber":null,"dateSigned":null,"strSigning":null,"strWage":null,"strOutfitter":null,"strKit":null,"strAgent":null,"strBirthLocation":", Norway","strEthnicity":null,"strStatus":null,"strDescriptionEN":null,"strDescriptionDE":null,"strDescriptionFR":null,"strDescriptionCN":null,"strDescriptionIT":null,"strDescriptionJP":null,"strDescriptionRU":null,"strDescriptionES":null,"strDescriptionPT":null,"strDescriptionSE":null,"strDescriptionNL":null,"strDescriptionHU":null,"strDescriptionNO":null,"strDescriptionIL":null,"strDescriptionPL":null,"strGender":"Male","strSide":null,"strPosition":"Defender","strCollege":null,"strFacebook":null,"strWebsite":null,"strTwitter":null,"strInstagram":null,"strYoutube":null,"strHeight":"","strWeight":"","intLoved":"0","strThumb":null,"strPoster":null,"strCutout":null,"strCartoon":null,"strRender":null,"strBanner":null,"strFanart1":null,"strFanart2":null,"strFanart3":null,"strFanart4":null,"strCreativeCommons":"No","strLocked":"unlocked","strLastName":"Helland"},{"idPlayer":"34175914","idTeam":"134571","idTeam2":"0","idTeamNational":null,"idAPIfootball":"145953","idPlayerManager":null,"idWikidata":null,"idTransferMkt":"455068","idESPN":"295848","strNationality":"Denmark","strPlayer":"Emil Kornvig","strPlayerAlternate":"","strTeam":"Brann","strTeam2":"","strSport":"Soccer","intSoccerXMLTeamID":null,"dateBorn":"2000-04-28","dateDied":null,"strNumber":"10","dateSigned":null,"strSigning":"On loan (Spezia)","strWage":"","strOutfitter":"","strKit":"","strAgent":"Elite Consulting","strBirthLocation":"Søborg, Denmark","strEthnicity":"White","strStatus":"Active","strDescriptionEN":"Emil Nestved Kornvig (Danish pronunciation: ; born 28 April 2000) is a Danish professional footballer who plays as a midfielder for Norwegian Eliteserien club Brann.\r\n\r\nCareer\r\nLyngby Boldklub\r\nKornvig progressed through the Lyngby Boldklub youth academy, before permanently being promoted to the first team in 2020. He tested positive for COVID-19 without symptoms on 23 September 2020 ahead of Lyngby's match against FC Nordsjælland. On 18 January 2021, he signed a contract extension keeping him at the club until 30 June 2024. He suffered relegation to the Danish 1st Division with the club on 9 May 2021 after a loss to last placed AC Horsens.\r\n\r\nSpezia\r\nOn 26 July 2021 he joined Serie A side Spezia.\r\n\r\nLoan to SønderjyskE\r\nOn the same day where he joined Spezia he went to SønderjyskE on loan.\r\n\r\nLoan to Cosenza\r\nOn 1 September 2022, Kornvig joined Cosenza on loan with an option to buy.\r\n\r\nCittadella\r\nOn 1 August 2023, Kornvig signed with Serie B club Cittadella.\r\n\r\nBrann\r\nAfter only half a season at Cittadella, Kornvig moved on to Norwegian top-flight club Brann in on 16 February 2024.","strDescriptionDE":null,"strDescriptionFR":null,"strDescriptionCN":null,"strDescriptionIT":null,"strDescriptionJP":null,"strDescriptionRU":null,"strDescriptionES":null,"strDescriptionPT":null,"strDescriptionSE":null,"strDescriptionNL":null,"strDescriptionHU":null,"strDescriptionNO":null,"strDescriptionIL":null,"strDescriptionPL":null,"strGender":"Male","strSide":"","strPosition":"Midfielder","strCollege":null,"strFacebook":"","strWebsite":"","strTwitter":"","strInstagram":"","strYoutube":"","strHeight":"","strWeight":"","intLoved":"0","strThumb":null,"strPoster":null,"strCutout":null,"strCartoon":null,"strRender":null,"strBanner":null,"strFanart1":null,"strFanart2":null,"strFanart3":null,"strFanart4":null,"strCreativeCommons":"No","strLocked":"unlocked","strLastName":"Kornvig"},{"idPlayer":"34145591","idTeam":"134571","idTeam2":null,"idTeamNational":null,"idAPIfootball":"39203","idPlayerManager":null,"idWikidata":null,"idTransferMkt":null,"idESPN":null,"strNationality":"Norway","strPlayer":"Erik Johansen","strPlayerAlternate":null,"strTeam":"Brann","strTeam2":null,"strSport":"Soccer","intSoccerXMLTeamID":"18","dateBorn":"1992-07-12","dateDied":null,"strNumber":null,"dateSigned":"2012-07-01","strSigning":"","strWage":"","strOutfitter":null,"strKit":null,"strAgent":null,"strBirthLocation":"\tTønsberg, Norway","strEthnicity":"White","strStatus":"Active","strDescriptionEN":"Eirik Holmen Johansen (born 12 July 1992) is a Norwegian footballer who plays as a goalkeeper for SK Brann. Johansen played for Teie IF in his native Norway before joining the Manchester City Academy system at the age of 16. Johansen has represented Norway at youth international level.","strDescriptionDE":null,"strDescriptionFR":null,"strDescriptionCN":null,"strDescriptionIT":null,"strDescriptionJP":null,"strDescriptionRU":null,"strDescriptionES":null,"strDescriptionPT":null,"strDescriptionSE":null,"strDescriptionNL":null,"strDescriptionHU":null,"strDescriptionNO":null,"strDescriptionIL":null,"strDescriptionPL":null,"strGender":"Male","strSide":null,"strPosition":"Goalkeeper","strCollege":null,"strFacebook":"","strWebsite":"","strTwitter":"","strInstagram":"","strYoutube":"","strHeight":"2.01 m","strWeight":"","intLoved":"0","strThumb":"https://r2.thesportsdb.com/images/media/player/thumb/vpxvvv1431646506.jpg","strPoster":null,"strCutout":null,"strCartoon":null,"strRender":null,"strBanner":null,"strFanart1":"https://r2.thesportsdb.com/images/media/player/fanart/tuxtxs1431646521.jpg","strFanart2":null,"strFanart3":null,"strFanart4":null,"strCreativeCommons":"No","strLocked":"unlocked","strLastName":"Johansen"},{"idPlayer":"34218146","idTeam":"134571","idTeam2":null,"idTeamNational":null,"idAPIfootball":"39066","idPlayerManager":null,"idWikidata":null,"idTransferMkt":null,"idESPN":"251618","strNationality":"Norway","strPlayer":"Felix Horn Myhre","strPlayerAlternate":null,"strTeam":"Brann","strTeam2":null,"strSport":"Soccer","intSoccerXMLTeamID":null,"dateBorn":"1999-03-04","dateDied":null,"strNumber":null,"dateSigned":null,"strSigning":null,"strWage":null,"strOutfitter":null,"strKit":null,"strAgent":null,"strBirthLocation":", Norway","strEthnicity":"White","strStatus":"Active","strDescriptionEN":null,"strDescriptionDE":null,"strDescriptionFR":null,"strDescriptionCN":null,"strDescriptionIT":null,"strDescriptionJP":null,"strDescriptionRU":null,"strDescriptionES":null,"strDescriptionPT":null,"strDescriptionSE":null,"strDescriptionNL":null,"strDescriptionHU":null,"strDescriptionNO":null,"strDescriptionIL":null,"strDescriptionPL":null,"strGender":"Male","strSide":null,"strPosition":"Midfielder","strCollege":null,"strFacebook":null,"strWebsite":null,"strTwitter":null,"strInstagram":null,"strYoutube":null,"strHeight":"180 cm","strWeight":"163 lbs","intLoved":"0","strThumb":null,"strPoster":null,"strCutout":null,"strCartoon":null,"strRender":null,"strBanner":null,"strFanart1":null,"strFanart2":null,"strFanart3":null,"strFanart4":null,"strCreativeCommons":"No","strLocked":"unlocked","strLastName":"Myhre"},{"idPlayer":"34237333","idTeam":"134571","idTeam2":null,"idTeamNational":null,"idAPIfootball":"39232","idPlayerManager":null,"idWikidata":"Q25429884","idTransferMkt":null,"idESPN":null,"strNationality":"Norway","strPlayer":"Fredrik Pallesen Knudsen","strPlayerAlternate":null,"strTeam":"Brann","strTeam2":null,"strSport":"Soccer","intSoccerXMLTeamID":null,"dateBorn":"1996-08-30","dateDied":null,"strNumber":null,"dateSigned":null,"strSigning":null,"strWage":null,"strOutfitter":null,"strKit":null,"strAgent":null,"strBirthLocation":"Bergen, Norway","strEthnicity":null,"strStatus":null,"strDescriptionEN":null,"strDescriptionDE":null,"strDescriptionFR":null,"strDescriptionCN":null,"strDescriptionIT":null,"strDescriptionJP":null,"strDescriptionRU":null,"strDescriptionES":null,"strDescriptionPT":null,"strDescriptionSE":null,"strDescriptionNL":null,"strDescriptionHU":null,"strDescriptionNO":null,"strDescriptionIL":null,"strDescriptionPL":null,"strGender":"Male","strSide":null,"strPosition":"Defender","strCollege":null,"strFacebook":null,"strWebsite":null,"strTwitter":null,"strInstagram":null,"strYoutube":null,"strHeight":"190 cm","strWeight":"83 kg","intLoved":"0","strThumb":null,"strPoster":null,"strCutout":null,"strCartoon":null,"strRender":null,"strBanner":null,"strFanart1":null,"strFanart2":null,"strFanart3":null,"strFanart4":null,"strCreativeCommons":"No","strLocked":"unlocked","strLastName":"Knudsen"},{"idPlayer":"34173235","idTeam":"134571","idTeam2":null,"idTeamNational":null,"idAPIfootball":"15832","idPlayerManager":null,"idWikidata":"Q26004790","idTransferMkt":null,"idESPN":null,"strNationality":"Denmark","strPlayer":"Jacob Sørensen","strPlayerAlternate":"Jacob Lungi Sörensen","strTeam":"Brann","strTeam2":"","strSport":"Soccer","intSoccerXMLTeamID":null,"dateBorn":"1998-03-03","dateDied":null,"strNumber":"19","dateSigned":null,"strSigning":"","strWage":"","strOutfitter":"","strKit":"","strAgent":"","strBirthLocation":"Esbjerg, Denmark","strEthnicity":"White","strStatus":"Active","strDescriptionEN":"Jacob Lungi Sørensen (born 3 March 1998) is a Danish professional footballer currently playing as a midfielder for Championship club Norwich City.\r\n\r\nClub career\r\nEsbjerg fB\r\nSørensen made his senior league debut for Esbjerg fB on 1 December 2016 in a Danish Superliga match away to Odense. The final score was 1-0 for Esbjerg fB. During his time at the club, he made 117 appearances and scored a total of 8 goals.\r\n\r\nNorwich City\r\nOn 20 July 2020, Sørensen signed a three-year contract with Norwich City. He made his debut against Brentford as a late replacement for Xavi Quintillà at left back, a position he had never played at before.","strDescriptionDE":null,"strDescriptionFR":null,"strDescriptionCN":null,"strDescriptionIT":null,"strDescriptionJP":null,"strDescriptionRU":null,"strDescriptionES":null,"strDescriptionPT":null,"strDescriptionSE":null,"strDescriptionNL":null,"strDescriptionHU":null,"strDescriptionNO":null,"strDescriptionIL":null,"strDescriptionPL":null,"strGender":"Male","strSide":"","strPosition":"Defensive Midfield","strCollege":null,"strFacebook":"","strWebsite":"","strTwitter":"","strInstagram":"","strYoutube":"","strHeight":"184 cm","strWeight":"","intLoved":"0","strThumb":"https://r2.thesportsdb.com/images/media/player/thumb/gz20ii1607547403.jpg","strPoster":null,"strCutout":"https://r2.thesportsdb.com/images/media/player/cutout/vr0vq31695293542.png","strCartoon":null,"strRender":"https://r2.thesportsdb.com/images/media/player/render/ls3i3a1637514387.png","strBanner":null,"strFanart1":null,"strFanart2":null,"strFanart3":null,"strFanart4":null,"strCreativeCommons":"No","strLocked":"unlocked","strLastName":"Sørensen"},{"idPlayer":"34196351","idTeam":"134571","idTeam2":"0","idTeamNational":null,"idAPIfootball":"64339","idPlayerManager":null,"idWikidata":null,"idTransferMkt":null,"idESPN":null,"strNationality":"Denmark","strPlayer":"Japhet Sery Larsen","strPlayerAlternate":"","strTeam":"Brann","strTeam2":"","strSport":"Soccer","intSoccerXMLTeamID":null,"dateBorn":"2000-04-10","dateDied":null,"strNumber":"","dateSigned":null,"strSigning":"","strWage":"","strOutfitter":"","strKit":"","strAgent":"","strBirthLocation":", Denmark","strEthnicity":"White","strStatus":"Active","strDescriptionEN":null,"strDescriptionDE":null,"strDescriptionFR":null,"strDescriptionCN":null,"strDescriptionIT":null,"strDescriptionJP":null,"strDescriptionRU":null,"strDescriptionES":null,"strDescriptionPT":null,"strDescriptionSE":null,"strDescriptionNL":null,"strDescriptionHU":null,"strDescriptionNO":null,"strDescriptionIL":null,"strDescriptionPL":null,"strGender":"Male","strSide":"","strPosition":"Defender","strCollege":null,"strFacebook":"","strWebsite":"","strTwitter":"","strInstagram":"","strYoutube":"","strHeight":"","strWeight":"","intLoved":"0","strThumb":null,"strPoster":null,"strCutout":null,"strCartoon":null,"strRender":null,"strBanner":null,"strFanart1":null,"strFanart2":null,"strFanart3":null,"strFanart4":null,"strCreativeCommons":"No","strLocked":"unlocked","strLastName":"Larsen"}]}